docs_agent/agents/__init__.py
docs_agent/agents/docs_agent.py
docs_agent/benchmarks/README.md
docs_agent/benchmarks/__init__.py
docs_agent/benchmarks/benchmarks.yaml
docs_agent/benchmarks/results.out
docs_agent/benchmarks/run_benchmark_tests.py
docs_agent/interfaces/README.md
docs_agent/interfaces/__init__.py
docs_agent/interfaces/chatbot/__init__.py
docs_agent/interfaces/chatbot/chatui.py
docs_agent/interfaces/chatbot/static/css/style-chatui-full.css
docs_agent/interfaces/chatbot/static/css/style-chatui-widget-pro.css
docs_agent/interfaces/chatbot/static/css/style-chatui-widget.css
docs_agent/interfaces/chatbot/static/css/style-chatui.css
docs_agent/interfaces/chatbot/static/css/style-logs.css
docs_agent/interfaces/chatbot/static/images/favicon.png
docs_agent/interfaces/chatbot/static/javascript/app.js
docs_agent/interfaces/chatbot/templates/admin/debugs.html
docs_agent/interfaces/chatbot/templates/admin/logs.html
docs_agent/interfaces/chatbot/templates/chatui/base.html
docs_agent/interfaces/chatbot/templates/chatui/index.html
docs_agent/interfaces/chatbot/templates/chatui/result.html
docs_agent/interfaces/chatbot/templates/chatui-experimental/base.html
docs_agent/interfaces/chatbot/templates/chatui-experimental/index.html
docs_agent/interfaces/chatbot/templates/chatui-experimental/result.html
docs_agent/interfaces/chatbot/templates/chatui-full/base.html
docs_agent/interfaces/chatbot/templates/chatui-full/index.html
docs_agent/interfaces/chatbot/templates/chatui-full/result.html
docs_agent/interfaces/chatbot/templates/chatui-widget/base.html
docs_agent/interfaces/chatbot/templates/chatui-widget/index.html
docs_agent/interfaces/chatbot/templates/chatui-widget/result.html
docs_agent/interfaces/chatbot/templates/chatui-widget-pro/base.html
docs_agent/interfaces/chatbot/templates/chatui-widget-pro/index.html
docs_agent/interfaces/chatbot/templates/chatui-widget-pro/result.html
docs_agent/interfaces/cli/__init__.py
docs_agent/interfaces/cli/cli.py
docs_agent-0.4.1.dist-info/LICENSE
docs_agent-0.4.1.dist-info/METADATA
docs_agent-0.4.1.dist-info/WHEEL
docs_agent-0.4.1.dist-info/entry_points.txt
docs_agent-0.4.1.dist-info/RECORD
