Metadata-Version: 2.1
Name: docs-agent
Version: 0.4.1
Summary: 
Author: Docs Agent contributors
Requires-Python: >=3.10,<3.12
Classifier: Programming Language :: Python :: 3
Classifier: Programming Language :: Python :: 3.10
Classifier: Programming Language :: Python :: 3.11
Requires-Dist: Markdown (>=3.4.3,<4.0.0)
Requires-Dist: absl-py (>=1.4.0,<2.0.0)
Requires-Dist: beautifulsoup4 (>=4.12.2,<5.0.0)
Requires-Dist: chromadb (>=0.4.22,<0.5.0)
Requires-Dist: click (>=8.1.7,<9.0.0)
Requires-Dist: flask (>=2.3.2,<3.0.0)
Requires-Dist: flatdict (>=4.0.1,<5.0.0)
Requires-Dist: google-generativeai (>=0.8.3,<0.9.0)
Requires-Dist: numpy (>=1.26.4,<2.0.0)
Requires-Dist: pillow (>=11.0.0,<12.0.0)
Requires-Dist: protobuf (>=3.20)
Requires-Dist: python-frontmatter (>=1.0.0,<2.0.0)
Requires-Dist: pytz (>=2020.1)
Requires-Dist: pyyaml (>=6.0.1,<7.0.0)
Requires-Dist: ratelimit (>=2.2.1,<3.0.0)
Requires-Dist: rich (>=13.3.5,<14.0.0)
Requires-Dist: tqdm (>=4.66.2,<5.0.0)
Requires-Dist: uuid (>=1.30,<2.0)
